{
  "name" : "Alcohol de-addiction program Enrolment",
  "uuid" : "1ae892bc-4c6e-49a5-a22e-002d061fae80",
  "formType" : "ProgramEnrolment",
  "formElementGroups" : [ {
    "uuid" : "dc370ba0-8d53-4b2d-8e1c-90b3a8815a69",
    "name" : "Identification",
    "displayOrder" : 1.0,
    "formElements" : [ {
      "name" : "Type of alcoholic",
      "uuid" : "30106962-77d2-4d92-8699-957a2f2f8c32",
      "keyValues" : [ ],
      "concept" : {
        "name" : "Type of alcoholic",
        "uuid" : "71f33845-7a28-4662-8b19-7589ca3e9bdc",
        "dataType" : "Coded",
        "answers" : [ {
          "name" : "Risky",
          "uuid" : "7bca7d99-0d3e-4f73-b7fc-56bd8ae26e3c",
          "dataType" : "NA",
          "answers" : [ ],
          "order" : 1.0,
          "active" : true,
          "media" : [ ]
        }, {
          "name" : "Severe",
          "uuid" : "23fb6352-06ed-4295-b971-47061306af50",
          "dataType" : "NA",
          "answers" : [ ],
          "order" : 3.0,
          "active" : true,
          "media" : [ ]
        }, {
          "name" : "Low risk",
          "uuid" : "5d6d3450-328d-47ff-b104-23bd5bc9a1ff",
          "dataType" : "NA",
          "answers" : [ ],
          "order" : 0.0,
          "active" : true,
          "media" : [ ]
        }, {
          "name" : "Harmful",
          "uuid" : "854971a0-069a-44bd-8488-86dda70f2ebe",
          "dataType" : "NA",
          "answers" : [ ],
          "order" : 2.0,
          "active" : true,
          "media" : [ ]
        } ],
        "active" : true,
        "media" : [ ]
      },
      "displayOrder" : 1.0,
      "type" : "SingleSelect",
      "mandatory" : true
    }, {
      "name" : "Duration of drinking habit (In months/years)",
      "uuid" : "cb27792f-11e2-4dd9-a101-244f1f41eb0c",
      "keyValues" : [ ],
      "concept" : {
        "name" : "Duration of drinking habit (In months/years)",
        "uuid" : "d2e81e44-3e72-42fb-8a1c-d64bceffd28e",
        "dataType" : "Text",
        "answers" : [ ],
        "active" : true,
        "media" : [ ]
      },
      "displayOrder" : 2.0,
      "type" : "SingleSelect",
      "mandatory" : true
    }, {
      "name" : "What led to alcohol consumption",
      "uuid" : "b7724d4e-75ed-4f5f-ab52-b4a4f23d3089",
      "keyValues" : [ ],
      "concept" : {
        "name" : "What led to alcohol consumption",
        "uuid" : "3511873d-85e4-4090-886c-46fc6c7dd6aa",
        "dataType" : "Coded",
        "answers" : [ {
          "name" : "Boredom",
          "uuid" : "d00c8dd5-38fc-4bf9-9b27-96d42e90e5fb",
          "dataType" : "NA",
          "answers" : [ ],
          "order" : 13.0,
          "active" : true,
          "media" : [ ]
        }, {
          "name" : "Sudden loss of loved one",
          "uuid" : "518e8b5d-7caa-4786-b536-ca9e2cc8bd1c",
          "dataType" : "NA",
          "answers" : [ ],
          "order" : 4.0,
          "active" : true,
          "media" : [ ]
        }, {
          "name" : "Poor family support",
          "uuid" : "b77c2140-154f-45f8-b0de-64f3f5667212",
          "dataType" : "NA",
          "answers" : [ ],
          "order" : 12.0,
          "active" : true,
          "media" : [ ]
        }, {
          "name" : "Poor social support",
          "uuid" : "6ef0c3f1-7268-4624-8df4-6dd59a282682",
          "dataType" : "NA",
          "answers" : [ ],
          "order" : 11.0,
          "active" : true,
          "media" : [ ]
        }, {
          "name" : "Low self esteem",
          "uuid" : "e23f383d-4851-43d8-a684-7d39fa596e55",
          "dataType" : "NA",
          "answers" : [ ],
          "order" : 8.0,
          "active" : true,
          "media" : [ ]
        }, {
          "name" : "Financial problems",
          "uuid" : "44c3416e-d955-4a9d-af5a-2224f8ff5859",
          "dataType" : "NA",
          "answers" : [ ],
          "order" : 9.0,
          "active" : true,
          "media" : [ ]
        }, {
          "name" : "Family conflict",
          "uuid" : "a22e3975-143c-49ed-8cbf-3ca069357b88",
          "dataType" : "NA",
          "answers" : [ ],
          "order" : 7.0,
          "active" : true,
          "media" : [ ]
        }, {
          "name" : "Easy access",
          "uuid" : "95683af5-81f4-4937-b045-7937a02f29eb",
          "dataType" : "NA",
          "answers" : [ ],
          "order" : 0.0,
          "active" : true,
          "media" : [ ]
        }, {
          "name" : "Grief",
          "uuid" : "3cdfb391-db97-42cf-aa9a-ab432b56f35d",
          "dataType" : "NA",
          "answers" : [ ],
          "order" : 5.0,
          "active" : true,
          "media" : [ ]
        }, {
          "name" : "Societal issues and cultures",
          "uuid" : "83c7b2a1-98b6-4910-8965-3dba4277526c",
          "dataType" : "NA",
          "answers" : [ ],
          "order" : 10.0,
          "active" : true,
          "media" : [ ]
        }, {
          "name" : "Rejection",
          "uuid" : "39127319-3b43-40d9-94eb-61ddae808373",
          "dataType" : "NA",
          "answers" : [ ],
          "order" : 6.0,
          "active" : true,
          "media" : [ ]
        }, {
          "name" : "Chronic ill-health",
          "uuid" : "a4ed2eac-f22c-4be9-959f-a7fd42900105",
          "dataType" : "NA",
          "answers" : [ ],
          "order" : 14.0,
          "active" : true,
          "media" : [ ]
        }, {
          "name" : "Physical exhaustion",
          "uuid" : "bb9ebebd-056d-4d9d-afe9-7aa81af22c4d",
          "dataType" : "NA",
          "answers" : [ ],
          "order" : 2.0,
          "active" : true,
          "media" : [ ]
        }, {
          "name" : "Others",
          "uuid" : "118fa43e-525f-41d6-ad3f-98a4857e2d3e",
          "dataType" : "NA",
          "answers" : [ ],
          "order" : 15.0,
          "active" : true,
          "media" : [ ]
        }, {
          "name" : "Low coping machanism to resist",
          "uuid" : "a2819323-37de-40bb-a448-c5fba5e25f52",
          "dataType" : "NA",
          "answers" : [ ],
          "order" : 1.0,
          "active" : true,
          "media" : [ ]
        }, {
          "name" : "Peer pressure",
          "uuid" : "50260ee3-ec4d-4eee-9706-f288b34b5385",
          "dataType" : "NA",
          "answers" : [ ],
          "order" : 3.0,
          "active" : true,
          "media" : [ ]
        } ],
        "active" : true,
        "media" : [ ]
      },
      "displayOrder" : 3.0,
      "type" : "MultiSelect",
      "mandatory" : true
    }, {
      "name" : "Are you on regular medication for any illness",
      "uuid" : "367b1e60-69e5-4063-955e-2005fb4711ed",
      "keyValues" : [ ],
      "concept" : {
        "name" : "Are you on regular medication for any illness",
        "uuid" : "6229d97b-45f4-459c-8c20-e7dcd67f98b8",
        "dataType" : "Coded",
        "answers" : [ {
          "name" : "Others",
          "uuid" : "118fa43e-525f-41d6-ad3f-98a4857e2d3e",
          "dataType" : "NA",
          "answers" : [ ],
          "order" : 7.0,
          "active" : true,
          "media" : [ ]
        }, {
          "name" : "None",
          "uuid" : "ebda5e05-a995-43ca-ad1a-30af3b937539",
          "dataType" : "NA",
          "answers" : [ ],
          "order" : 6.0,
          "active" : true,
          "media" : [ ]
        }, {
          "name" : "Cancer",
          "uuid" : "e8480835-eca9-44ff-920c-dd0c909a4492",
          "dataType" : "NA",
          "answers" : [ ],
          "order" : 5.0,
          "active" : true,
          "media" : [ ]
        }, {
          "name" : "Tuberculosis",
          "uuid" : "e6c6060e-6779-49ec-a13d-c1690f59c546",
          "dataType" : "NA",
          "answers" : [ ],
          "order" : 4.0,
          "active" : true,
          "media" : [ ]
        }, {
          "name" : "Diabetes",
          "uuid" : "674f348f-5075-4c85-8bc2-9edfdee27505",
          "dataType" : "NA",
          "answers" : [ ],
          "order" : 2.0,
          "active" : true,
          "media" : [ ]
        }, {
          "name" : "Hypertension",
          "uuid" : "998d1bae-05d8-47b9-89b8-0254829f238f",
          "dataType" : "NA",
          "answers" : [ ],
          "order" : 1.0,
          "active" : true,
          "media" : [ ]
        }, {
          "name" : "Mental health",
          "uuid" : "ca93e427-657b-4ed9-847c-da508b311949",
          "dataType" : "NA",
          "answers" : [ ],
          "order" : 0.0,
          "active" : true,
          "media" : [ ]
        }, {
          "name" : "Sickle Cell Disease",
          "uuid" : "06d65da3-a753-4f75-8d77-a3a1ce3fb75c",
          "dataType" : "NA",
          "answers" : [ ],
          "order" : 3.0,
          "active" : true,
          "media" : [ ]
        } ],
        "active" : true,
        "media" : [ ]
      },
      "displayOrder" : 4.0,
      "type" : "MultiSelect",
      "rule" : "'use strict';\n({params, imports}) => {\n  const programEnrolment = params.entity;\n  const formElement = params.formElement;\n  const statusBuilder = new imports.rulesConfig.FormElementStatusBuilder({programEnrolment, formElement});\n  statusBuilder.show().when.valueInEnrolment('What led to alcohol consumption').containsAnyAnswerConceptName('Chronic ill-health');\n  return statusBuilder.build();//this method returns FormElementStatus object with visibility true if the conditions given above matches\n};",
      "mandatory" : true
    }, {
      "name" : "Specify others",
      "uuid" : "bffc4959-6c68-47ae-b582-b086fe6a7d8b",
      "keyValues" : [ ],
      "concept" : {
        "name" : "Specify others",
        "uuid" : "39facae2-de63-4b3e-b0f1-ef32ce74afc2",
        "dataType" : "Text",
        "answers" : [ ],
        "active" : true,
        "keyValues" : [ ],
        "media" : [ ]
      },
      "displayOrder" : 5.0,
      "type" : "SingleSelect",
      "rule" : "'use strict';\n({params, imports}) => {\n  const programEnrolment = params.entity;\n  const formElement = params.formElement;\n  const statusBuilder = new imports.rulesConfig.FormElementStatusBuilder({programEnrolment, formElement});\n  statusBuilder.show().when.valueInEnrolment('What led to alcohol consumption').containsAnyAnswerConceptName('Others');\n  return statusBuilder.build();//this method returns FormElementStatus object with visibility true if the conditions given above matches\n};",
      "mandatory" : true
    }, {
      "name" : "Presenting complaints",
      "uuid" : "87ec474a-78d2-4418-a3a6-a311521f9fed",
      "keyValues" : [ ],
      "concept" : {
        "name" : "Presenting complaints",
        "uuid" : "266df9a6-e77d-464b-8c4a-d6f9bb4515b2",
        "dataType" : "Text",
        "answers" : [ ],
        "active" : true,
        "keyValues" : [ ],
        "media" : [ ]
      },
      "displayOrder" : 6.0,
      "type" : "SingleSelect",
      "mandatory" : true
    }, {
      "name" : "History of presenting complaints",
      "uuid" : "eb8faa61-71bf-4334-bc6b-e280b8c4e02e",
      "keyValues" : [ ],
      "concept" : {
        "name" : "History of presenting complaints",
        "uuid" : "f431ccd5-e10e-410f-a1dd-16dfe6b5b2e4",
        "dataType" : "Text",
        "answers" : [ ],
        "active" : true,
        "media" : [ ]
      },
      "displayOrder" : 7.0,
      "type" : "SingleSelect",
      "mandatory" : true
    }, {
      "name" : "Family history",
      "uuid" : "a0b946dd-1ac2-4b7d-aa79-5667b8449a02",
      "keyValues" : [ ],
      "concept" : {
        "name" : "Family history_",
        "uuid" : "ab39c9f6-c2b7-4e88-a477-e889866d4079",
        "dataType" : "Text",
        "answers" : [ ],
        "active" : true,
        "media" : [ ]
      },
      "displayOrder" : 8.0,
      "type" : "SingleSelect",
      "mandatory" : true
    }, {
      "name" : "Treatment history",
      "uuid" : "3d1fe205-71f0-4e4c-a09c-906d2980e282",
      "keyValues" : [ ],
      "concept" : {
        "name" : "Treatment history",
        "uuid" : "7f237785-48bf-4cfc-a21c-8d7a821245d8",
        "dataType" : "Text",
        "answers" : [ ],
        "active" : true,
        "keyValues" : [ ],
        "media" : [ ]
      },
      "displayOrder" : 9.0,
      "type" : "SingleSelect",
      "mandatory" : true
    } ],
    "display" : "Identification",
    "timed" : false
  } ],
  "decisionRule" : "",
  "visitScheduleRule" : "//SAMPLE RULE EXAMPLE\n\"use strict\";\n({ params, imports }) => {\n  const programEnrolment = params.entity;\n  const scheduleBuilder = new imports.rulesConfig.VisitScheduleBuilder({\n    programEnrolment\n  });\n  //add new visit schedule object to scheduleBuilder\n  scheduleBuilder\n    .add({\n      name: \"Alcohol de-addiction Follow up\",\n      encounterType: \"Alcohol de-addiction Follow up\",\n      earliestDate: programEnrolment.enrolmentDateTime,\n      maxDate: imports.moment(programEnrolment.enrolmentDateTime).add(20, 'days').toDate()\n    });\n  \n  return scheduleBuilder.getAll();\n};",
  "validationRule" : "",
  "checklistsRule" : "",
  "decisionConcepts" : [ ]
}