{
  "name" : "New born screening (Hospital)",
  "uuid" : "76c94d80-93cf-46d0-9b51-68f3cfbe2092",
  "formType" : "ProgramEncounter",
  "formElementGroups" : [ {
    "uuid" : "14c4ba0d-8b66-4f1d-950e-6dc5e454e890",
    "name" : "New born screening (Hospital)",
    "displayOrder" : 1.0,
    "formElements" : [ {
      "name" : "Date of delivery [H]",
      "uuid" : "1205b272-6a65-4e67-860b-e31f108e6bb8",
      "keyValues" : [ ],
      "concept" : {
        "name" : "Date of delivery [H]",
        "uuid" : "fecad1c8-898a-46a4-98a9-54dfd0ce4799",
        "dataType" : "Date",
        "answers" : [ ],
        "active" : true,
        "media" : [ ]
      },
      "displayOrder" : 1.0,
      "type" : "SingleSelect",
      "mandatory" : false
    }, {
      "name" : "Place of birth [H]",
      "uuid" : "e19c9ace-40f8-4d38-beac-d5102d489953",
      "keyValues" : [ ],
      "concept" : {
        "name" : "Place of birth [H]",
        "uuid" : "38122781-5e85-4330-a1b5-1fe1b7ec42a0",
        "dataType" : "Text",
        "answers" : [ ],
        "active" : true,
        "keyValues" : [ ],
        "media" : [ ]
      },
      "displayOrder" : 2.0,
      "type" : "SingleSelect",
      "mandatory" : false
    }, {
      "name" : "Baby sangam number [H]",
      "uuid" : "02b9e534-713c-4447-90fa-46b32c2b7d9b",
      "keyValues" : [ ],
      "concept" : {
        "name" : "Baby sangam number [H]",
        "uuid" : "626408a7-fb4c-41aa-8137-5bbb4a52ad09",
        "dataType" : "Text",
        "answers" : [ ],
        "active" : true,
        "media" : [ ]
      },
      "displayOrder" : 3.0,
      "type" : "SingleSelect",
      "mandatory" : false
    }, {
      "name" : "Mother sangam number [H]",
      "uuid" : "01e60370-f60d-48d7-b94a-76087d6c272e",
      "keyValues" : [ ],
      "concept" : {
        "name" : "Mother sangam number [H]",
        "uuid" : "2eb0457f-8340-466d-ba09-f3f2e3ad981c",
        "dataType" : "Text",
        "answers" : [ ],
        "active" : true,
        "media" : [ ]
      },
      "displayOrder" : 4.0,
      "type" : "SingleSelect",
      "mandatory" : false
    }, {
      "name" : "Name [H]",
      "uuid" : "6b83c613-c3e4-4a08-aadc-e089f887da6c",
      "keyValues" : [ ],
      "concept" : {
        "name" : "Name [H]",
        "uuid" : "53027e58-fe10-4a3e-99fd-a3eec60ba51b",
        "dataType" : "Text",
        "answers" : [ ],
        "active" : true,
        "media" : [ ]
      },
      "displayOrder" : 5.0,
      "type" : "SingleSelect",
      "mandatory" : false
    }, {
      "name" : "Scoring [H]",
      "uuid" : "cd41b6df-452b-4ab5-931f-e39f56d5bc2e",
      "keyValues" : [ ],
      "concept" : {
        "name" : "Scoring [H]",
        "uuid" : "5aaea253-0b8e-41d6-996b-33c7e170d96e",
        "dataType" : "Text",
        "answers" : [ ],
        "active" : true,
        "media" : [ ]
      },
      "displayOrder" : 6.0,
      "type" : "SingleSelect",
      "mandatory" : false
    }, {
      "name" : "Gender [H]",
      "uuid" : "bbe8a14b-dc41-4174-a8e4-add53258b96d",
      "keyValues" : [ ],
      "concept" : {
        "name" : "Gender [H]",
        "uuid" : "73c658eb-fc76-4a49-a17f-31d15b50ec8d",
        "dataType" : "Coded",
        "answers" : [ {
          "name" : "Male [H]",
          "uuid" : "f7bf7ee0-779d-48b7-9649-661ef993b412",
          "dataType" : "NA",
          "answers" : [ ],
          "order" : 2.0,
          "active" : true,
          "media" : [ ]
        }, {
          "name" : "Female [H]",
          "uuid" : "b77e28b2-f1f5-4114-ade8-f5955ee60739",
          "dataType" : "NA",
          "answers" : [ ],
          "order" : 1.0,
          "active" : true,
          "media" : [ ]
        } ],
        "active" : true,
        "media" : [ ]
      },
      "displayOrder" : 7.0,
      "type" : "SingleSelect",
      "mandatory" : false
    }, {
      "name" : "Other [H]",
      "uuid" : "b5960cc5-8193-4ea5-b2ff-662091a684d1",
      "keyValues" : [ ],
      "concept" : {
        "name" : "Other [H]",
        "uuid" : "e11b9a8d-1ffb-47f7-801c-7a8d8a17ee09",
        "dataType" : "Text",
        "answers" : [ ],
        "active" : true,
        "media" : [ ]
      },
      "displayOrder" : 8.0,
      "type" : "SingleSelect",
      "mandatory" : false
    }, {
      "name" : "Baby weight [H]",
      "uuid" : "0ec60189-e028-40a8-8de6-d2fde14a96e4",
      "keyValues" : [ ],
      "concept" : {
        "name" : "Baby weight [H]",
        "uuid" : "f6609c29-e955-4f10-b5e6-5bdfbbd64476",
        "dataType" : "Text",
        "answers" : [ ],
        "active" : true,
        "media" : [ ]
      },
      "displayOrder" : 9.0,
      "type" : "SingleSelect",
      "mandatory" : false
    }, {
      "name" : "MC [H]",
      "uuid" : "9dec2171-98cb-4407-a4a7-843d8003d386",
      "keyValues" : [ ],
      "concept" : {
        "name" : "MC [H]",
        "uuid" : "20b395b1-cdcc-4a42-b9b6-a231ef79b4b3",
        "dataType" : "Text",
        "answers" : [ ],
        "active" : true,
        "media" : [ ]
      },
      "displayOrder" : 10.0,
      "type" : "SingleSelect",
      "mandatory" : false
    }, {
      "name" : "HC [H]",
      "uuid" : "1c3e2970-f769-428a-8cb1-e27d059da1f2",
      "keyValues" : [ ],
      "concept" : {
        "name" : "HC [H]",
        "uuid" : "5155a83b-50d0-4c0d-8899-0a4b7e2fbda4",
        "dataType" : "Text",
        "answers" : [ ],
        "active" : true,
        "media" : [ ]
      },
      "displayOrder" : 11.0,
      "type" : "SingleSelect",
      "mandatory" : false
    }, {
      "name" : "CC [H]",
      "uuid" : "2a8f30a5-c759-40d0-90ed-31edfefe7f24",
      "keyValues" : [ ],
      "concept" : {
        "name" : "CC [H]",
        "uuid" : "48573843-83d8-4936-8f45-25fecebe2d2d",
        "dataType" : "Text",
        "answers" : [ ],
        "active" : true,
        "media" : [ ]
      },
      "displayOrder" : 12.0,
      "type" : "SingleSelect",
      "mandatory" : false
    }, {
      "name" : "BCG [H]",
      "uuid" : "cba1b77a-4af4-4dea-a05b-23915ab5cc67",
      "keyValues" : [ ],
      "concept" : {
        "name" : "BCG [H]",
        "uuid" : "3b23ddcc-0965-4a83-b9f7-6d1153a0589b",
        "dataType" : "Coded",
        "answers" : [ {
          "name" : "True [H]",
          "uuid" : "7e9a5117-bc2b-45e4-b92c-cd5796f9d36b",
          "dataType" : "NA",
          "answers" : [ ],
          "order" : 1.0,
          "active" : true,
          "media" : [ ]
        }, {
          "name" : "False [H]",
          "uuid" : "50b20dc3-41e9-4d9c-b2af-266647214c57",
          "dataType" : "NA",
          "answers" : [ ],
          "order" : 2.0,
          "active" : true,
          "media" : [ ]
        } ],
        "active" : true,
        "media" : [ ]
      },
      "displayOrder" : 13.0,
      "type" : "SingleSelect",
      "mandatory" : false
    }, {
      "name" : "OPV [H]",
      "uuid" : "741dd51f-d863-48f0-bdba-86a7e47528c1",
      "keyValues" : [ ],
      "concept" : {
        "name" : "OPV [H]",
        "uuid" : "0ec678f8-fcac-4056-a0d6-cd55c784fbd3",
        "dataType" : "Coded",
        "answers" : [ {
          "name" : "True [H]",
          "uuid" : "7e9a5117-bc2b-45e4-b92c-cd5796f9d36b",
          "dataType" : "NA",
          "answers" : [ ],
          "order" : 1.0,
          "active" : true,
          "media" : [ ]
        }, {
          "name" : "False [H]",
          "uuid" : "50b20dc3-41e9-4d9c-b2af-266647214c57",
          "dataType" : "NA",
          "answers" : [ ],
          "order" : 2.0,
          "active" : true,
          "media" : [ ]
        } ],
        "active" : true,
        "media" : [ ]
      },
      "displayOrder" : 14.0,
      "type" : "SingleSelect",
      "mandatory" : false
    }, {
      "name" : "Hepatitis B [H]",
      "uuid" : "b751a2b7-f98f-4725-8541-dce8fb3b9ec5",
      "keyValues" : [ ],
      "concept" : {
        "name" : "Hepatitis B [H]",
        "uuid" : "c87bb80b-690c-4953-9f7c-56eeac6d2de9",
        "dataType" : "Coded",
        "answers" : [ {
          "name" : "False [H]",
          "uuid" : "50b20dc3-41e9-4d9c-b2af-266647214c57",
          "dataType" : "NA",
          "answers" : [ ],
          "order" : 2.0,
          "active" : true,
          "media" : [ ]
        }, {
          "name" : "True [H]",
          "uuid" : "7e9a5117-bc2b-45e4-b92c-cd5796f9d36b",
          "dataType" : "NA",
          "answers" : [ ],
          "order" : 1.0,
          "active" : true,
          "media" : [ ]
        } ],
        "active" : true,
        "media" : [ ]
      },
      "displayOrder" : 15.0,
      "type" : "SingleSelect",
      "mandatory" : false
    }, {
      "name" : "Vitamin K [H]",
      "uuid" : "f23956a7-936f-4f22-97ec-2413d4616956",
      "keyValues" : [ ],
      "concept" : {
        "name" : "Vitamin K [H]",
        "uuid" : "2d031413-c72a-439b-a813-894c12a6cc66",
        "dataType" : "Coded",
        "answers" : [ {
          "name" : "False [H]",
          "uuid" : "50b20dc3-41e9-4d9c-b2af-266647214c57",
          "dataType" : "NA",
          "answers" : [ ],
          "order" : 2.0,
          "active" : true,
          "media" : [ ]
        }, {
          "name" : "True [H]",
          "uuid" : "7e9a5117-bc2b-45e4-b92c-cd5796f9d36b",
          "dataType" : "NA",
          "answers" : [ ],
          "order" : 1.0,
          "active" : true,
          "media" : [ ]
        } ],
        "active" : true,
        "media" : [ ]
      },
      "displayOrder" : 16.0,
      "type" : "SingleSelect",
      "mandatory" : false
    }, {
      "name" : "Newborn status [H]",
      "uuid" : "219bd93a-cbd5-4afb-b5ff-427deb4346af",
      "keyValues" : [ ],
      "concept" : {
        "name" : "Newborn status [H]",
        "uuid" : "1bbef608-7f9b-4230-bfd5-4135ef56b105",
        "dataType" : "Coded",
        "answers" : [ {
          "name" : "IUGR [H]",
          "uuid" : "d588a00d-8b07-4398-9710-360c2159081a",
          "dataType" : "NA",
          "answers" : [ ],
          "order" : 2.0,
          "active" : true,
          "media" : [ ]
        }, {
          "name" : "Preterm [H]",
          "uuid" : "cc067f2c-df9c-48dc-a085-84b66259c4ce",
          "dataType" : "NA",
          "answers" : [ ],
          "order" : 1.0,
          "active" : true,
          "media" : [ ]
        } ],
        "active" : true,
        "media" : [ ]
      },
      "displayOrder" : 17.0,
      "type" : "SingleSelect",
      "mandatory" : false
    }, {
      "name" : "Sickle cell screening status [H]",
      "uuid" : "99feff4c-1311-496a-8731-a4a8c92965c0",
      "keyValues" : [ ],
      "concept" : {
        "name" : "Sickle cell screening status [H]",
        "uuid" : "378a7946-b1ad-4b03-9357-b94aec23eacf",
        "dataType" : "Coded",
        "answers" : [ {
          "name" : "FA [H]",
          "uuid" : "a388aac0-4675-46c3-8e37-90c1e7414f63",
          "dataType" : "NA",
          "answers" : [ ],
          "order" : 2.0,
          "active" : true,
          "media" : [ ]
        }, {
          "name" : "FS [H]",
          "uuid" : "13b1dde4-6868-428a-9509-959606f49872",
          "dataType" : "NA",
          "answers" : [ ],
          "order" : 1.0,
          "active" : true,
          "media" : [ ]
        }, {
          "name" : "AF [H]",
          "uuid" : "2daa5c5f-3812-4676-a876-2891efd43169",
          "dataType" : "NA",
          "answers" : [ ],
          "order" : 3.0,
          "active" : true,
          "media" : [ ]
        }, {
          "name" : "FAS [H]",
          "uuid" : "895e4be8-c3df-4d87-bf2e-593f4a86de29",
          "dataType" : "NA",
          "answers" : [ ],
          "order" : 0.0,
          "active" : true,
          "media" : [ ]
        } ],
        "active" : true,
        "media" : [ ]
      },
      "displayOrder" : 18.0,
      "type" : "SingleSelect",
      "mandatory" : false
    }, {
      "name" : "Hearing status [H]",
      "uuid" : "cbe449ab-a78a-400c-9ec9-e7560dfa9845",
      "keyValues" : [ ],
      "concept" : {
        "name" : "Hearing status [H]",
        "uuid" : "ce875ac7-e0f8-4b18-8b4a-b8199223e225",
        "dataType" : "Coded",
        "answers" : [ {
          "name" : "Hearing Normal [H]",
          "uuid" : "baac1729-29bb-4fb0-a1c4-8e3a694cbeb8",
          "dataType" : "NA",
          "answers" : [ ],
          "order" : 1.0,
          "active" : true,
          "media" : [ ]
        }, {
          "name" : "Hearing Impaired [H]",
          "uuid" : "c6fe4946-fd6c-432a-a3c1-563dd6a9e5f9",
          "dataType" : "NA",
          "answers" : [ ],
          "order" : 2.0,
          "active" : true,
          "media" : [ ]
        } ],
        "active" : true,
        "media" : [ ]
      },
      "displayOrder" : 19.0,
      "type" : "SingleSelect",
      "mandatory" : false
    }, {
      "name" : "Physical newborn check completed [H]",
      "uuid" : "4334506c-9c1d-4755-9158-6dc51a18a09a",
      "keyValues" : [ ],
      "concept" : {
        "name" : "Physical newborn check completed [H]",
        "uuid" : "7c2668b1-46f6-4d95-a3e6-7ba8f3415f9e",
        "dataType" : "Coded",
        "answers" : [ {
          "name" : "False [H]",
          "uuid" : "50b20dc3-41e9-4d9c-b2af-266647214c57",
          "dataType" : "NA",
          "answers" : [ ],
          "order" : 2.0,
          "active" : true,
          "media" : [ ]
        }, {
          "name" : "True [H]",
          "uuid" : "7e9a5117-bc2b-45e4-b92c-cd5796f9d36b",
          "dataType" : "NA",
          "answers" : [ ],
          "order" : 1.0,
          "active" : true,
          "media" : [ ]
        } ],
        "active" : true,
        "media" : [ ]
      },
      "displayOrder" : 20.0,
      "type" : "SingleSelect",
      "mandatory" : false
    }, {
      "name" : "Sickle cell status of father [H]",
      "uuid" : "15c3276e-53ee-4ae6-8b5a-f24c06988974",
      "keyValues" : [ ],
      "concept" : {
        "name" : "Sickle cell status of father [H]",
        "uuid" : "16f5cd46-ae08-4da8-9133-e7a2d77a7d4a",
        "dataType" : "Coded",
        "answers" : [ {
          "name" : "AA [H]",
          "uuid" : "fb1f1bd1-e960-4c64-99ea-769ff3aae62a",
          "dataType" : "NA",
          "answers" : [ ],
          "order" : 1.0,
          "active" : true,
          "media" : [ ]
        }, {
          "name" : "AS [H]",
          "uuid" : "bf8858f0-cd84-4ae8-ba92-1e47117f0db4",
          "dataType" : "NA",
          "answers" : [ ],
          "order" : 2.0,
          "active" : true,
          "media" : [ ]
        }, {
          "name" : "Unknown [H]",
          "uuid" : "366f8801-0074-40f8-912f-81b1ec801706",
          "dataType" : "NA",
          "answers" : [ ],
          "order" : 3.0,
          "active" : true,
          "media" : [ ]
        }, {
          "name" : "SS [H]",
          "uuid" : "ff07f66c-8149-4cca-9ddb-13a399875630",
          "dataType" : "NA",
          "answers" : [ ],
          "order" : 4.0,
          "active" : true,
          "media" : [ ]
        } ],
        "active" : true,
        "media" : [ ]
      },
      "displayOrder" : 21.0,
      "type" : "SingleSelect",
      "mandatory" : false
    }, {
      "name" : "Sickle cell status of mother [H]",
      "uuid" : "609ba40d-ab04-4b1b-bedf-ea797dd80207",
      "keyValues" : [ ],
      "concept" : {
        "name" : "Sickle cell status of mother [H]",
        "uuid" : "f2aeb8c3-12fd-4608-9ab8-98208e8984d8",
        "dataType" : "Coded",
        "answers" : [ {
          "name" : "Unknown [H]",
          "uuid" : "366f8801-0074-40f8-912f-81b1ec801706",
          "dataType" : "NA",
          "answers" : [ ],
          "order" : 2.0,
          "active" : true,
          "media" : [ ]
        }, {
          "name" : "AA [H]",
          "uuid" : "fb1f1bd1-e960-4c64-99ea-769ff3aae62a",
          "dataType" : "NA",
          "answers" : [ ],
          "order" : 1.0,
          "active" : true,
          "media" : [ ]
        }, {
          "name" : "AS [H]",
          "uuid" : "bf8858f0-cd84-4ae8-ba92-1e47117f0db4",
          "dataType" : "NA",
          "answers" : [ ],
          "order" : 3.0,
          "active" : true,
          "media" : [ ]
        }, {
          "name" : "SS [H]",
          "uuid" : "ff07f66c-8149-4cca-9ddb-13a399875630",
          "dataType" : "NA",
          "answers" : [ ],
          "order" : 4.0,
          "active" : true,
          "media" : [ ]
        } ],
        "active" : true,
        "media" : [ ]
      },
      "displayOrder" : 22.0,
      "type" : "SingleSelect",
      "mandatory" : false
    }, {
      "name" : "Rattle test [H]",
      "uuid" : "3d58cb62-2680-40e9-ab62-8ebaacfc699e",
      "keyValues" : [ ],
      "concept" : {
        "name" : "Rattle test [H]",
        "uuid" : "1bc4063a-5738-4336-8456-ac11c27f67be",
        "dataType" : "Coded",
        "answers" : [ {
          "name" : "Refer [H]",
          "uuid" : "c3b89b08-9a72-48df-81a3-28e3e96e64e5",
          "dataType" : "NA",
          "answers" : [ ],
          "order" : 1.0,
          "active" : true,
          "media" : [ ]
        }, {
          "name" : "Pass [H]",
          "uuid" : "9ae21185-8a2b-4de1-9dee-9cfd5af9eca4",
          "dataType" : "NA",
          "answers" : [ ],
          "order" : 0.0,
          "active" : true,
          "media" : [ ]
        } ],
        "active" : true,
        "keyValues" : [ ],
        "media" : [ ]
      },
      "displayOrder" : 23.0,
      "type" : "SingleSelect",
      "mandatory" : false
    }, {
      "name" : "OAE test Right [H]",
      "uuid" : "fe588cc9-bed1-431a-bf4e-c0a400c7c4ab",
      "keyValues" : [ ],
      "concept" : {
        "name" : "OAE test Right [H]",
        "uuid" : "e5b5434f-8caa-4eb6-b883-f937e1103e28",
        "dataType" : "Coded",
        "answers" : [ {
          "name" : "Refer [H]",
          "uuid" : "c3b89b08-9a72-48df-81a3-28e3e96e64e5",
          "dataType" : "NA",
          "answers" : [ ],
          "order" : 1.0,
          "active" : true,
          "media" : [ ]
        }, {
          "name" : "Pass [H]",
          "uuid" : "9ae21185-8a2b-4de1-9dee-9cfd5af9eca4",
          "dataType" : "NA",
          "answers" : [ ],
          "order" : 0.0,
          "active" : true,
          "media" : [ ]
        } ],
        "active" : true,
        "keyValues" : [ ],
        "media" : [ ]
      },
      "displayOrder" : 24.0,
      "type" : "SingleSelect",
      "mandatory" : false
    }, {
      "name" : "OAE test Left [H]",
      "uuid" : "cfceceff-f0dd-4cfd-b7b1-e35cb93500e5",
      "keyValues" : [ ],
      "concept" : {
        "name" : "OAE test Left [H]",
        "uuid" : "dc8f4178-94f5-456e-aebd-9b3fa7e07916",
        "dataType" : "Coded",
        "answers" : [ {
          "name" : "Pass [H]",
          "uuid" : "9ae21185-8a2b-4de1-9dee-9cfd5af9eca4",
          "dataType" : "NA",
          "answers" : [ ],
          "order" : 0.0,
          "active" : true,
          "media" : [ ]
        }, {
          "name" : "Refer [H]",
          "uuid" : "c3b89b08-9a72-48df-81a3-28e3e96e64e5",
          "dataType" : "NA",
          "answers" : [ ],
          "order" : 1.0,
          "active" : true,
          "media" : [ ]
        } ],
        "active" : true,
        "keyValues" : [ ],
        "media" : [ ]
      },
      "displayOrder" : 25.0,
      "type" : "SingleSelect",
      "mandatory" : false
    }, {
      "name" : "Hearing Remark [H]",
      "uuid" : "b35ff5d1-91ff-46db-9305-8b09ec93d493",
      "keyValues" : [ ],
      "concept" : {
        "name" : "Hearing Remark [H]",
        "uuid" : "b1f1b365-1e68-44ce-88f6-d2d49c1ea75d",
        "dataType" : "Text",
        "answers" : [ ],
        "active" : true,
        "keyValues" : [ ],
        "media" : [ ]
      },
      "displayOrder" : 26.0,
      "type" : "SingleSelect",
      "mandatory" : false
    }, {
      "name" : "Any abnormalities found on physical examination [H]",
      "uuid" : "3f42f62b-c15a-461c-ae39-c90000ce85e1",
      "keyValues" : [ ],
      "concept" : {
        "name" : "Any abnormalities found on physical examination [H]",
        "uuid" : "e47f4b97-e4e9-4086-bcfc-53b665504cad",
        "dataType" : "Coded",
        "answers" : [ {
          "name" : "True [H]",
          "uuid" : "7e9a5117-bc2b-45e4-b92c-cd5796f9d36b",
          "dataType" : "NA",
          "answers" : [ ],
          "order" : 1.0,
          "active" : true,
          "media" : [ ]
        }, {
          "name" : "False [H]",
          "uuid" : "50b20dc3-41e9-4d9c-b2af-266647214c57",
          "dataType" : "NA",
          "answers" : [ ],
          "order" : 2.0,
          "active" : true,
          "media" : [ ]
        } ],
        "active" : true,
        "media" : [ ]
      },
      "displayOrder" : 27.0,
      "type" : "SingleSelect",
      "mandatory" : false
    } ],
    "display" : "New born screening (Hospital)",
    "timed" : false
  } ],
  "decisionRule" : "",
  "visitScheduleRule" : "",
  "validationRule" : "",
  "checklistsRule" : "",
  "decisionConcepts" : [ ]
}