{
  "uuid" : "f682f0d2-5dc5-451e-8626-f741034ba997",
  "settings" : {
    "languages" : [ "en", "hi_IN", "gu_IN" ],
    "copilotFormValidationApiKey" : "ze43nNV2kT19fVLV",
    "customRegistrationLocations" : [ {
      "subjectTypeUUID" : "92bf310a-6ddb-4010-8d44-d7cb009cbc9c",
      "locationTypeUUIDs" : [ "f59d29c2-dbfb-4c94-b1ff-41fb642c9291" ]
    }, {
      "subjectTypeUUID" : "816da5ca-d4df-449d-bcd4-8eef62930d5a",
      "locationTypeUUIDs" : [ "f59d29c2-dbfb-4c94-b1ff-41fb642c9291" ]
    }, {
      "subjectTypeUUID" : "cffd3a47-d8cb-4a6f-99fc-21fddfa94b44",
      "locationTypeUUIDs" : [ "f59d29c2-dbfb-4c94-b1ff-41fb642c9291" ]
    }, {
      "subjectTypeUUID" : "cd93d6db-d4be-47a0-9f84-d25391f90e77",
      "locationTypeUUIDs" : [ "f59d29c2-dbfb-4c94-b1ff-41fb642c9291" ]
    }, {
      "subjectTypeUUID" : "c26ea079-e6f5-451f-ba38-1ed55f5860a9",
      "locationTypeUUIDs" : [ "f59d29c2-dbfb-4c94-b1ff-41fb642c9291" ]
    }, {
      "subjectTypeUUID" : "b3b98338-35af-4f29-a74d-3c8999d92165",
      "locationTypeUUIDs" : [ "f59d29c2-dbfb-4c94-b1ff-41fb642c9291" ]
    }, {
      "subjectTypeUUID" : "0720e6cc-f0e2-4019-aeb6-b3fba472aa4b",
      "locationTypeUUIDs" : [ "f59d29c2-dbfb-4c94-b1ff-41fb642c9291" ]
    }, {
      "subjectTypeUUID" : "0bc1dbf5-6790-4c9b-b5eb-d241ec6b0379",
      "locationTypeUUIDs" : [ "f59d29c2-dbfb-4c94-b1ff-41fb642c9291" ]
    }, {
      "subjectTypeUUID" : "0ab6edd4-2a80-4ce9-9bfa-0464cb4ae6b0",
      "locationTypeUUIDs" : [ "f59d29c2-dbfb-4c94-b1ff-41fb642c9291" ]
    }, {
      "subjectTypeUUID" : "cadc8363-b121-4cd4-bbbf-5bee4fd620d1",
      "locationTypeUUIDs" : [ "f25882dc-2a0f-4267-ae88-7ae4bfb264ee" ]
    }, {
      "subjectTypeUUID" : "a92cdaae-19cd-4778-920c-235e30c5ecdf",
      "locationTypeUUIDs" : [ "f59d29c2-dbfb-4c94-b1ff-41fb642c9291" ]
    } ],
    "saveDrafts" : true,
    "searchResultFields" : [ {
      "subjectTypeName" : "Influencing State",
      "subjectTypeUUID" : "cffd3a47-d8cb-4a6f-99fc-21fddfa94b44",
      "searchResultConcepts" : [ {
        "name" : "Created By Name",
        "uuid" : "5d9875ad-9f13-4243-8e1f-edfe00c18866",
        "displayOrder" : 1
      } ]
    }, {
      "subjectTypeName" : "Campaign",
      "subjectTypeUUID" : "0ab6edd4-2a80-4ce9-9bfa-0464cb4ae6b0",
      "searchResultConcepts" : [ {
        "name" : "Created By Name",
        "uuid" : "5d9875ad-9f13-4243-8e1f-edfe00c18866",
        "displayOrder" : 1
      } ]
    }, {
      "subjectTypeName" : "Case",
      "subjectTypeUUID" : "0bc1dbf5-6790-4c9b-b5eb-d241ec6b0379",
      "searchResultConcepts" : [ {
        "name" : "Created By Name",
        "uuid" : "5d9875ad-9f13-4243-8e1f-edfe00c18866",
        "displayOrder" : 1
      } ]
    }, {
      "subjectTypeName" : "Outreach",
      "subjectTypeUUID" : "a92cdaae-19cd-4778-920c-235e30c5ecdf",
      "searchResultConcepts" : [ {
        "name" : "Created By Name",
        "uuid" : "5d9875ad-9f13-4243-8e1f-edfe00c18866",
        "displayOrder" : 1
      } ]
    }, {
      "subjectTypeName" : "Claim",
      "subjectTypeUUID" : "cd93d6db-d4be-47a0-9f84-d25391f90e77",
      "searchResultConcepts" : [ {
        "name" : "Created By Username",
        "uuid" : "836f9b19-bebb-4295-8519-9c7c6a4e4d15",
        "displayOrder" : 1
      } ]
    } ],
    "metabaseSetupEnabled" : true,
    "lowestAddressLevelType" : [ "2588.2589.2590.2591", "2592.2593.2594.2595", "2915.2916.2917.2918", "2919.2920.2921.2922" ],
    "searchFilters" : [ {
      "type" : "Concept",
      "scope" : "registration",
      "widget" : "Default",
      "titleKey" : "Campaign Name",
      "conceptName" : "Campaign Name (Search)",
      "conceptUUID" : "e17aba43-433c-43c0-a7e7-d7f5a79ed244",
      "conceptDataType" : "Text",
      "scopeParameters" : {
        "programUUIDs" : [ ],
        "encounterTypeUUIDs" : [ ]
      },
      "subjectTypeUUID" : "a92cdaae-19cd-4778-920c-235e30c5ecdf"
    }, {
      "type" : "Concept",
      "scope" : "registration",
      "widget" : "Default",
      "titleKey" : "Username",
      "conceptName" : "Created By Name",
      "conceptUUID" : "5d9875ad-9f13-4243-8e1f-edfe00c18866",
      "conceptDataType" : "Text",
      "scopeParameters" : {
        "programUUIDs" : [ ],
        "encounterTypeUUIDs" : [ ]
      },
      "subjectTypeUUID" : "0bc1dbf5-6790-4c9b-b5eb-d241ec6b0379"
    }, {
      "type" : "Concept",
      "scope" : "registration",
      "widget" : "Default",
      "titleKey" : "Username",
      "conceptName" : "Created By Username",
      "conceptUUID" : "836f9b19-bebb-4295-8519-9c7c6a4e4d15",
      "conceptDataType" : "Text",
      "scopeParameters" : {
        "programUUIDs" : [ ],
        "encounterTypeUUIDs" : [ ]
      },
      "subjectTypeUUID" : "cffd3a47-d8cb-4a6f-99fc-21fddfa94b44"
    }, {
      "type" : "Concept",
      "scope" : "registration",
      "widget" : "Default",
      "titleKey" : "Username",
      "conceptName" : "Created By Username",
      "conceptUUID" : "836f9b19-bebb-4295-8519-9c7c6a4e4d15",
      "conceptDataType" : "Text",
      "scopeParameters" : {
        "programUUIDs" : [ ],
        "encounterTypeUUIDs" : [ ]
      },
      "subjectTypeUUID" : "a92cdaae-19cd-4778-920c-235e30c5ecdf"
    }, {
      "type" : "Concept",
      "scope" : "registration",
      "widget" : "Default",
      "titleKey" : "Username",
      "conceptName" : "Created By Username",
      "conceptUUID" : "836f9b19-bebb-4295-8519-9c7c6a4e4d15",
      "conceptDataType" : "Text",
      "scopeParameters" : {
        "programUUIDs" : [ ],
        "encounterTypeUUIDs" : [ ]
      },
      "subjectTypeUUID" : "cd93d6db-d4be-47a0-9f84-d25391f90e77"
    }, {
      "type" : "Concept",
      "scope" : "registration",
      "widget" : "Default",
      "titleKey" : "Username",
      "conceptName" : "Created By Username",
      "conceptUUID" : "836f9b19-bebb-4295-8519-9c7c6a4e4d15",
      "conceptDataType" : "Text",
      "scopeParameters" : {
        "programUUIDs" : [ ],
        "encounterTypeUUIDs" : [ ]
      },
      "subjectTypeUUID" : "816da5ca-d4df-449d-bcd4-8eef62930d5a"
    }, {
      "type" : "Concept",
      "scope" : "registration",
      "widget" : "Default",
      "titleKey" : "Username",
      "conceptName" : "Created By Username",
      "conceptUUID" : "836f9b19-bebb-4295-8519-9c7c6a4e4d15",
      "conceptDataType" : "Text",
      "scopeParameters" : {
        "programUUIDs" : [ ],
        "encounterTypeUUIDs" : [ ]
      },
      "subjectTypeUUID" : "92bf310a-6ddb-4010-8d44-d7cb009cbc9c"
    }, {
      "type" : "Concept",
      "scope" : "registration",
      "widget" : "Default",
      "titleKey" : "Username",
      "conceptName" : "Created By Username",
      "conceptUUID" : "836f9b19-bebb-4295-8519-9c7c6a4e4d15",
      "conceptDataType" : "Text",
      "scopeParameters" : {
        "programUUIDs" : [ ],
        "encounterTypeUUIDs" : [ ]
      },
      "subjectTypeUUID" : "0720e6cc-f0e2-4019-aeb6-b3fba472aa4b"
    }, {
      "type" : "Concept",
      "scope" : "registration",
      "widget" : "Default",
      "titleKey" : "Username",
      "conceptName" : "Created By Username",
      "conceptUUID" : "836f9b19-bebb-4295-8519-9c7c6a4e4d15",
      "conceptDataType" : "Text",
      "scopeParameters" : {
        "programUUIDs" : [ ],
        "encounterTypeUUIDs" : [ ]
      },
      "subjectTypeUUID" : "b3b98338-35af-4f29-a74d-3c8999d92165"
    }, {
      "type" : "Concept",
      "scope" : "registration",
      "titleKey" : "Username",
      "conceptName" : "Created By Username",
      "conceptUUID" : "836f9b19-bebb-4295-8519-9c7c6a4e4d15",
      "conceptDataType" : "Text",
      "scopeParameters" : {
        "programUUIDs" : [ ],
        "encounterTypeUUIDs" : [ ]
      },
      "subjectTypeUUID" : "c26ea079-e6f5-451f-ba38-1ed55f5860a9"
    } ],
    "myDashboardFilters" : [ ]
  },
  "worklistUpdationRule" : "({ params, imports }) => {\n  const workLists = params.workLists;\n  const context = params.context;\n  const WorkItem = imports.models.WorkItem;\n  const currentWorkItem = workLists.getCurrentWorkItem();\n\n  function generateUUID() {\n      const timestamp = new Date().getTime();\n      return 'xxxxxxxx-xxxx-4xxx-yxxx-xxxxxxxxxxxx'.replace(/[xy]/g, function (c) {\n          const r = (timestamp + Math.random() * 16) % 16 | 0;\n          return (c === 'x' ? r : (r & 0x3 | 0x8)).toString(16);\n      });\n  }\n  \n\n  function registrationWorkFlow() {\n      const individual = context.entity;\n      const currentWorkList = workLists.currentWorkList;\n      currentWorkList.workItems.splice(0, currentWorkList.workItems.length);\n      if (currentWorkItem.parameters.subjectTypeName === 'Campaign') {\n          currentWorkList.workItems.splice(\n              0,\n              currentWorkList.workItems.length,\n              new WorkItem(\"39c684ad-e72b-40ac-b353-ddb50e05c58c\",\n                  WorkItem.type.REGISTRATION,\n                  {\n                      subjectTypeName: \"Outreach\",\n                      saveAndProceedLabel: \"Register Outreach\"\n                  })\n          );\n      }\n      \n      if (currentWorkItem.parameters.subjectTypeName === 'Claim') {\n      \n          currentWorkList.workItems.splice(\n              0,\n              currentWorkList.workItems.length,\n              new WorkItem(\"94d1567c-3614-4b5b-9e84-39a1c55390ce\",\n                  WorkItem.type.PROGRAM_ENROLMENT,\n                 {\n                     subjectTypeName: \"Claim\",\n                     subjectUUID: individual.uuid,\n                     saveAndProceedLabel: \"Enrol to Claim Status\",\n                     programName: \"Claim Status\"\n                  })\n          );\n      }\n      if (currentWorkItem.parameters.subjectTypeName === 'Outreach') {\n          currentWorkList.workItems.splice(\n              0,\n              currentWorkList.workItems.length,\n              new WorkItem(\"8b9ba76f-bf61-4b9c-9b82-4399a2d44e8f\",\n                  WorkItem.type.ENCOUNTER,\n                  {\n                      encounterTypeName: \"Outreach Location Specific Details\",\n                      subjectTypeName: 'Outreach',\n                      subjectUUID: individual.uuid,\n                      encounterType: \"Outreach Location Specific Details\"\n                  })\n          );\n      }\n      if (currentWorkItem.parameters.subjectTypeName === 'Case') {\n          currentWorkList.workItems.splice(\n              0,\n              currentWorkList.workItems.length,\n              new WorkItem(\"9690aae8-95a8-48a7-b8b8-d208c70fe282\",\n                  WorkItem.type.PROGRAM_ENROLMENT,\n                 {\n                     subjectTypeName: \"Case\",\n                     subjectUUID: individual.uuid,\n                     saveAndProceedLabel: \"Enrol to Case Status\",\n                     programName: \"Case Status\"\n                  })\n          );\n      }\n     \n     const observationKey = \"387e72d2-1ced-4032-b273-ea3ef5c5a159\";\n     const singleEventUUID = \"9d91df97-79f6-4e42-8d61-19d8926edd9f\";\n     const phasedUUID = \"cfdfb311-ac5d-48ff-b250-57259194016b\";\n     const internalTraining = \"3feb2dac-7f40-49e7-82c8-a5c55b3feb8a\";\n     const externalTraining = \"f882e2b6-52e1-43cf-a45b-215e76ff05eb\";\n     const typeOfTraining = individual.getObservationValue(\"c7afa395-baae-4434-b8f7-b938b78051bd\");\n     const observationValue = individual.getObservationValue(observationKey);\n     const isSingleEvent = observationValue === singleEventUUID;\n     const isPhaseWise = observationValue === phasedUUID;\n\n     const hasTrainingAlreadyFilled = (type) => \n  individual.getEncounters(true).some(enc => \n    enc.encounterType.name === type && !enc.voided && enc.encounterDateTime == null\n  );\n\n  const hasOneTimeTrainingAlreadyFilled = hasTrainingAlreadyFilled(\"One Time Training\");\n  const hasInternalTrainingAlreadyFilled = hasTrainingAlreadyFilled(\"Internal Training\");\n  const hasExternalTrainingAlreadyFilled = hasTrainingAlreadyFilled(\"External Training\");\n\n     \nfunction replaceWorkItems(workList, workItemId, workItemType, params) {\n    workList.workItems.splice(0, workList.workItems.length, new WorkItem(workItemId, workItemType, params));\n}\n\nif (currentWorkItem.parameters.subjectTypeName === 'Training') {\n    if (isSingleEvent && !hasOneTimeTrainingAlreadyFilled) {\n        replaceWorkItems(currentWorkList, \"cc6181b4-8656-4527-8c99-96ae75f07906\", WorkItem.type.ENCOUNTER, {\n            encounterTypeName: \"One Time Training\",\n            subjectTypeName: 'Training',\n            subjectUUID: individual.uuid,\n            encounterType: \"One Time Training\"\n        });\n    } else if (isPhaseWise) {\n        if (typeOfTraining == internalTraining && !hasInternalTrainingAlreadyFilled) {\n            replaceWorkItems(currentWorkList, \"99a0a00b-37b0-4cbd-805f-33abbb137018\", WorkItem.type.ENCOUNTER, {\n                encounterTypeName: \"Internal Training\",\n                subjectTypeName: 'Training',\n                subjectUUID: individual.uuid,\n                encounterType: \"Internal Training\"\n            });\n        } \n        else if (!hasExternalTrainingAlreadyFilled) {  \n            if (typeOfTraining == externalTraining) {\n                replaceWorkItems(currentWorkList, \"23030d1b-7a0b-438a-870d-51c4c2d07e1c\", WorkItem.type.ENCOUNTER, {\n                    encounterTypeName: \"External Training\",\n                    subjectTypeName: 'Training',\n                    subjectUUID: individual.uuid,\n                    encounterType: \"External Training\"\n                });\n            } else {\n                replaceWorkItems(currentWorkList, \"6b48c60c-8a2e-4d05-827b-92181495069b\", WorkItem.type.REGISTRATION, {\n                    subjectTypeName: \"Training\",\n                    saveAndProceedLabel: \"Register Another Training\"\n                });\n            }\n        }\n    } else {\n        replaceWorkItems(currentWorkList, \"6b48c60c-8a2e-4d05-827b-92181495069b\", WorkItem.type.REGISTRATION, {\n            subjectTypeName: \"Training\",\n            saveAndProceedLabel: \"Register Another Training\"\n        });\n    }\n}\n\n\n  \n  const natureOfEngagement = individual.getObservationReadableValue('f304d6c0-dc78-4373-b584-b91d269d0835');\n\nconst hasAlreadyEnrolledInLetter = individual.enrolments.some(enl=>\n    enl.program.name === 'Letter Status' \n    && enl.programExitDateTime == null \n    && !enl.voided);\n\nconst hasAlreadyEnrolledInRTI = individual.enrolments.some(enl=>\n        enl.program.name === 'RTI Status' \n        && enl.programExitDateTime == null \n        && !enl.voided);\n\nconst hasAlreadyEnrolledInPIL = individual.enrolments.some(enl=>\n            enl.program.name === 'PIL Status' \n            && enl.programExitDateTime == null \n            && !enl.voided);\n        \nif(currentWorkItem.parameters.subjectTypeName === 'Influencing State'){\n    if(natureOfEngagement === 'Letter' && !hasAlreadyEnrolledInLetter){\n    currentWorkList.workItems.splice(\n        0,\n        currentWorkList.workItems.length,\n        new WorkItem(\"1e41369d-4ee1-4648-a552-9581a2801c75\",\n            WorkItem.type.PROGRAM_ENROLMENT,\n           {\n               subjectTypeName: \"Influencing State\",\n               subjectUUID: individual.uuid,\n               saveAndProceedLabel: \"Enrol to Letter status\",\n               programName: \"Letter Status\"\n            })\n    );\n} else if(natureOfEngagement === 'PIL' && !hasAlreadyEnrolledInPIL){\n    currentWorkList.workItems.splice(\n        0,\n        currentWorkList.workItems.length,\n        new WorkItem(\"9103d9f0-5a22-4358-8a6b-a0f52540b326\",\n            WorkItem.type.PROGRAM_ENROLMENT,\n           {\n               subjectTypeName: \"Influencing State\",\n               subjectUUID: individual.uuid,\n               saveAndProceedLabel: \"Enrol to PIL status\",\n               programName: \"PIL Status\"\n            })\n    );\n} else if(natureOfEngagement === 'Independent RTI' && !hasAlreadyEnrolledInRTI){\n    currentWorkList.workItems.splice(\n        0,\n        currentWorkList.workItems.length,\n        new WorkItem(\"8509bf0f-0180-4ff8-b6ff-384a72cb84fb\",\n            WorkItem.type.PROGRAM_ENROLMENT,\n           {\n               subjectTypeName: \"Influencing State\",\n               subjectUUID: individual.uuid,\n               saveAndProceedLabel: \"Enrol to RTI status\",\n               programName: \"RTI Status\"\n            })\n    );\n}\n}   \n}\n\n  function encounterWorkFlow() {\n      const currentWorkList = workLists.currentWorkList;\n      const generalEncounter = context.entity;\n      let encounters = generalEncounter.individual.getEncounters(true);\n      let isEncPresent = encounters.some((enl) => enl.uuid === generalEncounter.uuid);\n      \n      if(currentWorkItem.parameters.encounterType === 'Case Status Details'){\n          currentWorkList.workItems.splice(\n              0,\n              currentWorkList.workItems.length,\n              new WorkItem(\"8d8058d4-723a-411e-8670-5d8998ac87d6\",\n                  WorkItem.type.ENCOUNTER,\n                  {\n                      encounterTypeName: \"Case Activity Register\",\n                      subjectTypeName: 'Case',\n                      subjectUUID: generalEncounter.individual.uuid,\n                      encounterType: \"Case Activity Register\"\n                  })\n          );\n      }\n      \n      if (currentWorkItem.parameters.encounterType === 'Outreach Location Specific Details' && !isEncPresent) {\n          let outreachVisit = generalEncounter.getObservationReadableValue('59a812b5-511d-44a5-99ef-a963881a6864');\n          console.log('generalEncounter--->',generalEncounter)\n\n          if (outreachVisit === 'Yes') {\n              currentWorkList.workItems.splice(\n                  0,\n                  currentWorkList.workItems.length,\n                  new WorkItem(generateUUID(),\n                      WorkItem.type.ENCOUNTER,\n                      {\n                          encounterTypeName: \"Outreach Location Specific Details\",\n                          subjectTypeName: 'Outreach',\n                          subjectUUID: generalEncounter.individual.uuid,\n                          encounterType: \"Outreach Location Specific Details\"\n                      })\n              );\n          } else {\n              currentWorkList.workItems.splice(\n                  0,\n                  currentWorkList.workItems.length,\n                  new WorkItem(generateUUID(),\n                      WorkItem.type.ADD_MEMBER,\n                      {\n                          groupSubjectUUID: generalEncounter.individual.uuid,\n                          subjectTypeName: \"Issues Identified\",\n                          saveAndProceedLabel: \"Register Issues Identified\"\n                      })\n              );\n          }\n      }\n  }\n\n  function enrolmentWorkFlow() {\n      const currentWorkList = workLists.currentWorkList;\n      const enrolment = context.entity;\n      const individual = enrolment.individual;\n      let allEnrolments = enrolment.individual.enrolments;\n      let isEnlPresent = allEnrolments.some((enl) => enl.uuid === enrolment.uuid);\n\n      if (currentWorkItem.parameters.programName === \"Outreach Clients\" && !isEnlPresent) {\n          currentWorkList.workItems.splice(\n              0,\n              currentWorkList.workItems.length,\n              new WorkItem(generateUUID(),\n                  WorkItem.type.PROGRAM_ENCOUNTER,\n                  {\n                      encounterType: 'Client Follow Up',\n                      subjectUUID: enrolment.individual.uuid\n                  })\n          );\n      }    \n      if (currentWorkItem.parameters.programName === \"Letter Status\") {\n        const activeEnrolment = individual.enrolments.find(enrl =>\n          enrl.program.name === \"Letter Status\" &&\n          !enrl.voided &&\n          enrl.enrolmentDateTime &&\n          !enrl.programExitDateTime\n        );\n      \n        const shouldAddWorkItem = !activeEnrolment || \n          activeEnrolment.getEncountersOfType('Letter Document').length === 0;\n      \n        if (shouldAddWorkItem) {\n          const subjectUUID = activeEnrolment ? activeEnrolment.individual.uuid : enrolment.individual.uuid;\n      \n          currentWorkList.workItems.splice(\n            0,\n            currentWorkList.workItems.length,\n            new WorkItem(generateUUID(), WorkItem.type.PROGRAM_ENCOUNTER, {\n              encounterType: 'Letter Document',\n              subjectUUID: subjectUUID\n            })\n          );\n        }\n      }\n  }\n\n  function programEncounterWorkFlow() {\n      const currentWorkList = workLists.currentWorkList;\n      const programEncounter = context.entity;\n\n      let encounters = programEncounter.programEnrolment.getEncounters(true);\n      let isEncPresent = encounters.some((enc) => enc.uuid === programEncounter.uuid);\n\n      let doYouHaveMoreIssues = programEncounter.getObservationReadableValue('51400375-9167-44cd-93b9-4d19d79f8c68');\n      let followUpStatus = programEncounter.getObservationReadableValue('e26a61db-d7bf-4fbe-b5e2-ed60294e8f62');\n\n      if (currentWorkItem.parameters.encounterType === \"Client Follow Up\" && doYouHaveMoreIssues === 'Yes' && !isEncPresent) {\n          currentWorkList.workItems.splice(\n              0,\n              currentWorkList.workItems.length,\n              new WorkItem(generateUUID(),\n                  WorkItem.type.PROGRAM_ENROLMENT,\n                  {\n                      programName: \"Outreach Clients\",\n                      subjectUUID: programEncounter.individual.uuid\n                  })\n          );\n      } else if (currentWorkItem.parameters.encounterType === \"Client Follow Up\" && followUpStatus === 'Follow-up required' && !isEncPresent) {\n          currentWorkList.workItems.splice(\n              0,\n              currentWorkList.workItems.length,\n              new WorkItem(generateUUID(),\n                  WorkItem.type.PROGRAM_ENCOUNTER,\n                  {\n                      encounterType: 'Client Follow Up',\n                      subjectUUID: programEncounter.individual.uuid\n                  })\n          );\n      } else {\n          currentWorkList.workItems.splice(\n              0,\n              currentWorkList.workItems.length\n          );\n      }\n      \n      /*if (currentWorkItem.parameters.encounterType === \"Follow Up Letter\" && !isEncPresent) {\n          currentWorkList.workItems.splice(\n              0,\n              currentWorkList.workItems.length,\n              new WorkItem(generateUUID(),\n                  WorkItem.type.PROGRAM_ENCOUNTER,\n                  {\n                      encounterType: 'Letter Document',\n                      subjectUUID: programEncounter.individual.uuid\n                  })\n          );\n      }\n      if (currentWorkItem.parameters.encounterType === \"Follow Up RTI\" && !isEncPresent) {\n          currentWorkList.workItems.splice(\n              0,\n              currentWorkList.workItems.length,\n              new WorkItem(generateUUID(),\n                  WorkItem.type.PROGRAM_ENCOUNTER,\n                  {\n                      encounterType: 'Letter Document',\n                      subjectUUID: programEncounter.individual.uuid\n                  })\n          );\n      }*/\n  }\n  \n\n  const main = () => {\n      switch (currentWorkItem.type) {\n          case 'REGISTRATION':\n              registrationWorkFlow();\n              break;\n          case 'ENCOUNTER':\n              encounterWorkFlow();\n              break;\n          case 'PROGRAM_ENROLMENT':\n              enrolmentWorkFlow();\n              break;\n          case 'PROGRAM_ENCOUNTER':\n              programEncounterWorkFlow();\n              break;\n      }\n\n\n      return workLists;\n  };\n  \n\n  return main();\n};\n\n"
}