[ {
  "name" : "TIMS for Poshan Sathi",
  "uuid" : "542e9019-04c8-4aec-9801-26a7be8a39ad",
  "active" : true,
  "type" : "User",
  "subjectSummaryRule" : "",
  "programEligibilityCheckRule" : "",
  "allowEmptyLocation" : true,
  "allowMiddleName" : false,
  "lastNameOptional" : false,
  "allowProfilePicture" : false,
  "uniqueName" : false,
  "shouldSyncByLocation" : false,
  "settings" : {
    "displayRegistrationDetails" : true,
    "displayPlannedEncounters" : true
  },
  "household" : false,
  "group" : false,
  "directlyAssignable" : false,
  "voided" : false
}, {
  "name" : "Village Profile",
  "uuid" : "bfc36f13-831c-445a-ada9-5696840f8cee",
  "active" : true,
  "type" : "Individual",
  "subjectSummaryRule" : "",
  "programEligibilityCheckRule" : "",
  "allowEmptyLocation" : false,
  "allowMiddleName" : false,
  "lastNameOptional" : false,
  "allowProfilePicture" : false,
  "uniqueName" : false,
  "shouldSyncByLocation" : true,
  "settings" : {
    "displayRegistrationDetails" : true,
    "displayPlannedEncounters" : true
  },
  "household" : false,
  "group" : false,
  "directlyAssignable" : false,
  "voided" : false
}, {
  "name" : "Household",
  "uuid" : "f2ffc396-2acc-4e97-af90-d9585eb2df75",
  "active" : true,
  "type" : "Group",
  "subjectSummaryRule" : "",
  "programEligibilityCheckRule" : "",
  "allowEmptyLocation" : false,
  "allowMiddleName" : false,
  "lastNameOptional" : false,
  "allowProfilePicture" : false,
  "uniqueName" : false,
  "shouldSyncByLocation" : true,
  "settings" : {
    "displayRegistrationDetails" : true,
    "displayPlannedEncounters" : true
  },
  "household" : false,
  "group" : true,
  "directlyAssignable" : false,
  "voided" : false
}, {
  "name" : "AWC Profile",
  "uuid" : "eb642a9c-ae1b-4247-81ba-87800227d981",
  "active" : true,
  "type" : "Individual",
  "subjectSummaryRule" : "",
  "programEligibilityCheckRule" : "",
  "allowEmptyLocation" : false,
  "allowMiddleName" : false,
  "lastNameOptional" : false,
  "allowProfilePicture" : false,
  "uniqueName" : false,
  "shouldSyncByLocation" : true,
  "settings" : {
    "displayRegistrationDetails" : true,
    "displayPlannedEncounters" : true
  },
  "household" : false,
  "group" : false,
  "directlyAssignable" : false,
  "voided" : false
}, {
  "name" : "Individual",
  "uuid" : "ec69af69-8fd2-40b3-b429-025504c18a01",
  "active" : true,
  "type" : "Person",
  "subjectSummaryRule" : "//SAMPLE RULE EXAMPLE\n'use strict';\n({params, imports}) =>  {\n  const {summaries, individual} = params;\n  const highRiskValue = individual.getObservationReadableValue('To be monitored by QRT')[0];\n    if(highRiskValue == 'Yes'){\n        const highrisk =  individual.findObservation('To be monitored by QRT');\n        summaries.push({name: 'To be monitored by QRT', value: highrisk.getValue()});\n    }\n  return summaries;\n};",
  "programEligibilityCheckRule" : "",
  "allowEmptyLocation" : false,
  "allowMiddleName" : false,
  "lastNameOptional" : false,
  "allowProfilePicture" : false,
  "uniqueName" : false,
  "shouldSyncByLocation" : true,
  "syncRegistrationConcept1" : "be0ab05f-b0f3-43ec-b598-fdde0679104a",
  "settings" : {
    "displayRegistrationDetails" : true,
    "displayPlannedEncounters" : true
  },
  "household" : false,
  "group" : false,
  "syncRegistrationConcept1Usable" : true,
  "directlyAssignable" : false,
  "voided" : false
}, {
  "name" : "AWC area inputs (voided~562)",
  "uuid" : "387cc2ab-3981-4ffd-85fa-faf9fdb04150",
  "active" : true,
  "type" : "Individual",
  "subjectSummaryRule" : "",
  "programEligibilityCheckRule" : "",
  "allowEmptyLocation" : false,
  "allowMiddleName" : false,
  "lastNameOptional" : false,
  "allowProfilePicture" : false,
  "uniqueName" : false,
  "shouldSyncByLocation" : true,
  "settings" : {
    "displayRegistrationDetails" : true,
    "displayPlannedEncounters" : true
  },
  "household" : false,
  "group" : false,
  "directlyAssignable" : false,
  "voided" : true
} ]